handyscope/__init__.py
handyscope/config.json
handyscope/device.py
handyscope/deviceList.py
handyscope/generator.py
handyscope/i2cHost.py
handyscope/jitter_free.py
handyscope/library.py
handyscope/oscilloscope.py
handyscope/oscilloscopeChannel.py
handyscope/triggerInput.py
handyscope/triggerOutput.py
handyscope/bin/libtiepie.so
handyscope/bin/libtiepie32.dll
handyscope/bin/libtiepie64.dll
handyscope-1.1.0.dist-info/AUTHORS.rst
handyscope-1.1.0.dist-info/LICENSE
handyscope-1.1.0.dist-info/LICENSE_bundled.txt
handyscope-1.1.0.dist-info/METADATA
handyscope-1.1.0.dist-info/WHEEL
handyscope-1.1.0.dist-info/top_level.txt
handyscope-1.1.0.dist-info/RECORD
