Metadata-Version: 2.1
Name: handyscope
Version: 1.1.0
Summary: Handyscope provides a Python interface to the mobile USB-oscilloscopes made by TiePie.
Home-page: http://emt.uni-paderborn.de
Author: Tim Hetkaemper
Author-email: timh1@mail.uni-paderborn.de
License: BSD
Classifier: Development Status :: 2 - Pre-Alpha
Classifier: Intended Audience :: Science/Research
Classifier: License :: OSI Approved :: BSD License
Classifier: Programming Language :: Python :: 3
Classifier: Topic :: Scientific/Engineering
License-File: LICENSE
License-File: LICENSE_bundled.txt
License-File: AUTHORS.rst
Requires-Dist: numpy
Requires-Dist: scipy
